MANIFEST.in
setup.py
bsc/__init__.py
bsc/_bsc.c
bsc/_bsc.pyx
bsc/bsc.c
bsc/bsc.cpp
bsc.egg-info/PKG-INFO
bsc.egg-info/SOURCES.txt
bsc.egg-info/dependency_links.txt
bsc.egg-info/requires.txt
bsc.egg-info/top_level.txt
bsc/libbsc/bsc.cpp
bsc/libbsc/filters.h
bsc/libbsc/libbsc.h
bsc/libbsc/makefile
bsc/libbsc/adler32/adler32.cpp
bsc/libbsc/adler32/adler32.h
bsc/libbsc/bwt/bwt.cpp
bsc/libbsc/bwt/bwt.h
bsc/libbsc/bwt/divsufsort/divsufsort.c
bsc/libbsc/bwt/divsufsort/divsufsort.h
bsc/libbsc/coder/coder.cpp
bsc/libbsc/coder/coder.h
bsc/libbsc/coder/common/predictor.h
bsc/libbsc/coder/common/rangecoder.h
bsc/libbsc/coder/common/tables.h
bsc/libbsc/coder/qlfc/qlfc.cpp
bsc/libbsc/coder/qlfc/qlfc.h
bsc/libbsc/coder/qlfc/qlfc_model.cpp
bsc/libbsc/coder/qlfc/qlfc_model.h
bsc/libbsc/filters/detectors.cpp
bsc/libbsc/filters/preprocessing.cpp
bsc/libbsc/filters/tables.h
bsc/libbsc/libbsc/libbsc.cpp
bsc/libbsc/lzp/lzp.cpp
bsc/libbsc/lzp/lzp.h
bsc/libbsc/platform/platform.cpp
bsc/libbsc/platform/platform.h
bsc/libbsc/st/st.cpp
bsc/libbsc/st/st.cuh
bsc/libbsc/st/st.h
bsc/libbsc/st/b40c/radix_sort/cta_radix_rank.cuh
bsc/libbsc/st/b40c/radix_sort/enactor.cuh
bsc/libbsc/st/b40c/radix_sort/pass_policy.cuh
bsc/libbsc/st/b40c/radix_sort/problem_instance.cuh
bsc/libbsc/st/b40c/radix_sort/sort_utils.cuh
bsc/libbsc/st/b40c/radix_sort/downsweep/cta.cuh
bsc/libbsc/st/b40c/radix_sort/downsweep/kernel.cuh
bsc/libbsc/st/b40c/radix_sort/downsweep/kernel_policy.cuh
bsc/libbsc/st/b40c/radix_sort/downsweep/tex_ref.cuh
bsc/libbsc/st/b40c/radix_sort/spine/cta.cuh
bsc/libbsc/st/b40c/radix_sort/spine/kernel.cuh
bsc/libbsc/st/b40c/radix_sort/spine/kernel_policy.cuh
bsc/libbsc/st/b40c/radix_sort/upsweep/cta.cuh
bsc/libbsc/st/b40c/radix_sort/upsweep/kernel.cuh
bsc/libbsc/st/b40c/radix_sort/upsweep/kernel_policy.cuh
bsc/libbsc/st/b40c/util/allocator.cuh
bsc/libbsc/st/b40c/util/basic_utils.cuh
bsc/libbsc/st/b40c/util/cta_work_distribution.cuh
bsc/libbsc/st/b40c/util/cuda_properties.cuh
bsc/libbsc/st/b40c/util/device_intrinsics.cuh
bsc/libbsc/st/b40c/util/error_utils.cuh
bsc/libbsc/st/b40c/util/kernel_props.cuh
