Metadata-Version: 1.2
Name: bsc
Version: 0.1.2
Summary: Python binding for libbsc, a fast yet capable compressor
Home-page: http://github.com/observerss/bsc
Author: Jingchao Hu
Author-email: jingchaohu@gmail.com
License: UNKNOWN
Platform: UNKNOWN
Classifier: Development Status :: 4 - Beta
Classifier: Intended Audience :: Developers
Classifier: Topic :: System :: Archiving :: Compression
Classifier: License :: OSI Approved :: MIT License
Classifier: Programming Language :: Python :: 3
Requires-Python: >=3.5
